pywatts/__init__.py
pywatts/callbacks/__init__.py
pywatts/callbacks/base_callback.py
pywatts/callbacks/csv_callback.py
pywatts/callbacks/debug_callback.py
pywatts/callbacks/plot_callback.py
pywatts/conditions/__init__.py
pywatts/conditions/periodic_condition.py
pywatts/core/__init__.py
pywatts/core/base.py
pywatts/core/base_condition.py
pywatts/core/base_step.py
pywatts/core/base_summary.py
pywatts/core/computation_mode.py
pywatts/core/either_or_step.py
pywatts/core/filemanager.py
pywatts/core/inverse_step.py
pywatts/core/pipeline.py
pywatts/core/pipeline_step.py
pywatts/core/probabilistic_step.py
pywatts/core/result_step.py
pywatts/core/run_setting.py
pywatts/core/start_step.py
pywatts/core/step.py
pywatts/core/step_factory.py
pywatts/core/step_information.py
pywatts/core/summary_formatter.py
pywatts/core/summary_object.py
pywatts/core/summary_step.py
pywatts/core/template.py
pywatts/core/exceptions/__init__.py
pywatts/core/exceptions/input_not_available.py
pywatts/core/exceptions/invalid_input_exception.py
pywatts/core/exceptions/io_exceptions.py
pywatts/core/exceptions/kind_of_transform_does_not_exist_exception.py
pywatts/core/exceptions/not_fitted_exception.py
pywatts/core/exceptions/step_creation_exception.py
pywatts/core/exceptions/util_exception.py
pywatts/core/exceptions/wrong_parameter_exception.py
pywatts/modules/__init__.py
pywatts/modules/feature_extraction/__init__.py
pywatts/modules/feature_extraction/calendar_extraction.py
pywatts/modules/feature_extraction/rolling_base.py
pywatts/modules/feature_extraction/rolling_kurtosis.py
pywatts/modules/feature_extraction/rolling_mean.py
pywatts/modules/feature_extraction/rolling_skewness.py
pywatts/modules/feature_extraction/rolling_variance.py
pywatts/modules/feature_extraction/trend_extraction.py
pywatts/modules/generation/__init__.py
pywatts/modules/generation/anomaly_generation_module.py
pywatts/modules/generation/energy_anomaly_generation_module.py
pywatts-0.3.0.dist-info/LICENSE
pywatts-0.3.0.dist-info/METADATA
pywatts-0.3.0.dist-info/WHEEL
pywatts-0.3.0.dist-info/top_level.txt
pywatts-0.3.0.dist-info/RECORD
